[
  {
    "id": "2025-08-29 04:07:22",
    "wagerRequirement": 500,
    "casino": "Horseshoe",
    "date": "08/29",
    "link": "https://horseshoeonlinecasino.com/us/mi/mypromos",
    "deposit": 75,
    "bonus": 25,
    "strategy": {
      "5": {
        "normal": {
          "mean": "23.40",
          "riskOfRuin": "5.85%",
          "stdDev": "52.51",
          "meanExcludingFirstLoss": "23.40",
          "stdDevExcludingFirstLoss": "52.51",
          "chanceToProfit": "66.07%"
        },
        "half2x": {
          "mean": "23.26",
          "riskOfRuin": "50.09%",
          "stdDev": "117.93",
          "meanExcludingFirstLoss": "163.20",
          "stdDevExcludingFirstLoss": "54.48",
          "chanceToProfit": "42.89%"
        },
        "half3x": {
          "mean": "23.24",
          "riskOfRuin": "53.88%",
          "stdDev": "144.27",
          "meanExcludingFirstLoss": "273.48",
          "stdDevExcludingFirstLoss": "59.91",
          "chanceToProfit": "35.21%"
        },
        "full2x": {
          "mean": "23.94",
          "riskOfRuin": "52.53%",
          "stdDev": "123.94",
          "meanExcludingFirstLoss": "144.36",
          "stdDevExcludingFirstLoss": "60.71",
          "chanceToProfit": "47.27%"
        },
        "full4x": {
          "mean": "24.03",
          "riskOfRuin": "74.10%",
          "stdDev": "205.69",
          "meanExcludingFirstLoss": "391.91",
          "stdDevExcludingFirstLoss": "98.32",
          "chanceToProfit": "23.83%"
        },
        "rpsFlat": {
          "mean": "8.33",
          "riskOfRuin": "0.00%",
          "stdDev": "17.36",
          "meanExcludingFirstLoss": "8.33",
          "stdDevExcludingFirstLoss": "17.36",
          "chanceToProfit": "68.52%"
        },
        "rpsHalf2x": {
          "mean": "20.19",
          "riskOfRuin": "50.02%",
          "stdDev": "111.93",
          "meanExcludingFirstLoss": "154.19",
          "stdDevExcludingFirstLoss": "39.76",
          "chanceToProfit": "43.01%"
        },
        "rpsHalf3x": {
          "mean": "22.30",
          "riskOfRuin": "53.82%",
          "stdDev": "141.94",
          "meanExcludingFirstLoss": "267.34",
          "stdDevExcludingFirstLoss": "51.99",
          "chanceToProfit": "35.25%"
        },
        "rpsFull2x": {
          "mean": "18.51",
          "riskOfRuin": "52.50%",
          "stdDev": "114.73",
          "meanExcludingFirstLoss": "132.77",
          "stdDevExcludingFirstLoss": "41.98",
          "chanceToProfit": "47.48%"
        },
        "rpsFull4x": {
          "mean": "22.87",
          "riskOfRuin": "74.09%",
          "stdDev": "203.21",
          "meanExcludingFirstLoss": "386.13",
          "stdDevExcludingFirstLoss": "93.33",
          "chanceToProfit": "23.82%"
        }
      },
      "10": {
        "normal": {
          "mean": "23.46",
          "riskOfRuin": "17.65%",
          "stdDev": "72.38",
          "meanExcludingFirstLoss": "23.46",
          "stdDevExcludingFirstLoss": "72.38",
          "chanceToProfit": "60.00%"
        },
        "half2x": {
          "mean": "23.41",
          "riskOfRuin": "50.06%",
          "stdDev": "120.53",
          "meanExcludingFirstLoss": "163.29",
          "stdDevExcludingFirstLoss": "68.14",
          "chanceToProfit": "42.62%"
        },
        "half3x": {
          "mean": "23.31",
          "riskOfRuin": "53.83%",
          "stdDev": "144.98",
          "meanExcludingFirstLoss": "273.51",
          "stdDevExcludingFirstLoss": "68.91",
          "chanceToProfit": "35.23%"
        },
        "full2x": {
          "mean": "23.97",
          "riskOfRuin": "52.58%",
          "stdDev": "128.02",
          "meanExcludingFirstLoss": "144.31",
          "stdDevExcludingFirstLoss": "76.53",
          "chanceToProfit": "46.07%"
        },
        "full4x": {
          "mean": "24.03",
          "riskOfRuin": "74.10%",
          "stdDev": "206.26",
          "meanExcludingFirstLoss": "391.98",
          "stdDevExcludingFirstLoss": "103.49",
          "chanceToProfit": "23.81%"
        },
        "rpsFlat": {
          "mean": "8.34",
          "riskOfRuin": "0.06%",
          "stdDev": "24.54",
          "meanExcludingFirstLoss": "8.34",
          "stdDevExcludingFirstLoss": "24.54",
          "chanceToProfit": "63.21%"
        },
        "rpsHalf2x": {
          "mean": "20.17",
          "riskOfRuin": "50.03%",
          "stdDev": "112.25",
          "meanExcludingFirstLoss": "154.22",
          "stdDevExcludingFirstLoss": "41.99",
          "chanceToProfit": "42.97%"
        },
        "rpsHalf3x": {
          "mean": "22.22",
          "riskOfRuin": "53.86%",
          "stdDev": "141.99",
          "meanExcludingFirstLoss": "267.46",
          "stdDevExcludingFirstLoss": "53.29",
          "chanceToProfit": "35.22%"
        },
        "rpsFull2x": {
          "mean": "18.51",
          "riskOfRuin": "52.50%",
          "stdDev": "115.23",
          "meanExcludingFirstLoss": "132.81",
          "stdDevExcludingFirstLoss": "44.61",
          "chanceToProfit": "47.48%"
        },
        "rpsFull4x": {
          "mean": "22.96",
          "riskOfRuin": "74.09%",
          "stdDev": "203.38",
          "meanExcludingFirstLoss": "386.36",
          "stdDevExcludingFirstLoss": "94.21",
          "chanceToProfit": "23.83%"
        }
      },
      "15": {
        "normal": {
          "mean": "23.53",
          "riskOfRuin": "25.10%",
          "stdDev": "86.80",
          "meanExcludingFirstLoss": "23.53",
          "stdDevExcludingFirstLoss": "86.80",
          "chanceToProfit": "57.10%"
        },
        "half2x": {
          "mean": "23.27",
          "riskOfRuin": "50.19%",
          "stdDev": "123.00",
          "meanExcludingFirstLoss": "163.31",
          "stdDevExcludingFirstLoss": "79.59",
          "chanceToProfit": "42.05%"
        },
        "half3x": {
          "mean": "23.29",
          "riskOfRuin": "53.85%",
          "stdDev": "145.67",
          "meanExcludingFirstLoss": "273.47",
          "stdDevExcludingFirstLoss": "76.77",
          "chanceToProfit": "35.22%"
        },
        "full2x": {
          "mean": "24.00",
          "riskOfRuin": "52.91%",
          "stdDev": "131.93",
          "meanExcludingFirstLoss": "144.42",
          "stdDevExcludingFirstLoss": "89.38",
          "chanceToProfit": "44.67%"
        },
        "full4x": {
          "mean": "23.83",
          "riskOfRuin": "74.12%",
          "stdDev": "206.46",
          "meanExcludingFirstLoss": "391.55",
          "stdDevExcludingFirstLoss": "107.93",
          "chanceToProfit": "23.80%"
        },
        "rpsFlat": {
          "mean": "8.35",
          "riskOfRuin": "0.48%",
          "stdDev": "30.00",
          "meanExcludingFirstLoss": "8.35",
          "stdDevExcludingFirstLoss": "30.00",
          "chanceToProfit": "60.97%"
        },
        "rpsHalf2x": {
          "mean": "20.18",
          "riskOfRuin": "50.03%",
          "stdDev": "112.55",
          "meanExcludingFirstLoss": "154.25",
          "stdDevExcludingFirstLoss": "44.08",
          "chanceToProfit": "42.97%"
        },
        "rpsHalf3x": {
          "mean": "22.17",
          "riskOfRuin": "53.87%",
          "stdDev": "142.08",
          "meanExcludingFirstLoss": "267.37",
          "stdDevExcludingFirstLoss": "54.36",
          "chanceToProfit": "35.19%"
        },
        "rpsFull2x": {
          "mean": "18.49",
          "riskOfRuin": "52.51%",
          "stdDev": "115.68",
          "meanExcludingFirstLoss": "132.79",
          "stdDevExcludingFirstLoss": "47.18",
          "chanceToProfit": "47.47%"
        },
        "rpsFull4x": {
          "mean": "22.84",
          "riskOfRuin": "74.10%",
          "stdDev": "203.33",
          "meanExcludingFirstLoss": "386.26",
          "stdDevExcludingFirstLoss": "94.65",
          "chanceToProfit": "23.80%"
        }
      },
      "20": {
        "normal": {
          "mean": "23.64",
          "riskOfRuin": "33.16%",
          "stdDev": "97.45",
          "meanExcludingFirstLoss": "23.64",
          "stdDevExcludingFirstLoss": "97.45",
          "chanceToProfit": "53.77%"
        },
        "half2x": {
          "mean": "23.33",
          "riskOfRuin": "50.29%",
          "stdDev": "125.39",
          "meanExcludingFirstLoss": "163.17",
          "stdDevExcludingFirstLoss": "89.45",
          "chanceToProfit": "41.56%"
        },
        "half3x": {
          "mean": "23.28",
          "riskOfRuin": "53.85%",
          "stdDev": "146.33",
          "meanExcludingFirstLoss": "273.61",
          "stdDevExcludingFirstLoss": "84.05",
          "chanceToProfit": "35.23%"
        },
        "full2x": {
          "mean": "23.88",
          "riskOfRuin": "53.57%",
          "stdDev": "135.82",
          "meanExcludingFirstLoss": "144.31",
          "stdDevExcludingFirstLoss": "101.01",
          "chanceToProfit": "43.29%"
        },
        "full4x": {
          "mean": "23.96",
          "riskOfRuin": "74.09%",
          "stdDev": "207.15",
          "meanExcludingFirstLoss": "391.74",
          "stdDevExcludingFirstLoss": "113.23",
          "chanceToProfit": "23.83%"
        },
        "rpsFlat": {
          "mean": "8.36",
          "riskOfRuin": "1.43%",
          "stdDev": "34.58",
          "meanExcludingFirstLoss": "8.36",
          "stdDevExcludingFirstLoss": "34.58",
          "chanceToProfit": "59.78%"
        },
        "rpsHalf2x": {
          "mean": "20.02",
          "riskOfRuin": "50.10%",
          "stdDev": "112.80",
          "meanExcludingFirstLoss": "154.24",
          "stdDevExcludingFirstLoss": "46.06",
          "chanceToProfit": "42.91%"
        },
        "rpsHalf3x": {
          "mean": "22.22",
          "riskOfRuin": "53.84%",
          "stdDev": "142.14",
          "meanExcludingFirstLoss": "267.38",
          "stdDevExcludingFirstLoss": "55.46",
          "chanceToProfit": "35.21%"
        },
        "rpsFull2x": {
          "mean": "18.45",
          "riskOfRuin": "52.51%",
          "stdDev": "116.13",
          "meanExcludingFirstLoss": "132.72",
          "stdDevExcludingFirstLoss": "49.54",
          "chanceToProfit": "47.46%"
        },
        "rpsFull4x": {
          "mean": "22.71",
          "riskOfRuin": "74.14%",
          "stdDev": "203.30",
          "meanExcludingFirstLoss": "386.21",
          "stdDevExcludingFirstLoss": "95.22",
          "chanceToProfit": "23.78%"
        }
      }
    }
  },
  {
    "id": "2025-08-29 04:25:41",
    "wagerRequirement": 2500,
    "casino": "Caesars",
    "date": "08/29",
    "link": "https://caesarspalaceonline.com/us/mi/mypromos",
    "deposit": 75,
    "bonus": 25,
    "strategy": {
      "5": {
        "normal": {
          "mean": "18.47",
          "riskOfRuin": "41.96%",
          "stdDev": "102.87",
          "meanExcludingFirstLoss": "18.47",
          "stdDevExcludingFirstLoss": "102.87",
          "chanceToProfit": "48.53%"
        },
        "half2x": {
          "mean": "20.60",
          "riskOfRuin": "60.90%",
          "stdDev": "137.80",
          "meanExcludingFirstLoss": "159.30",
          "stdDevExcludingFirstLoss": "117.46",
          "chanceToProfit": "37.11%"
        },
        "half3x": {
          "mean": "21.08",
          "riskOfRuin": "73.07%",
          "stdDev": "171.09",
          "meanExcludingFirstLoss": "282.77",
          "stdDevExcludingFirstLoss": "121.70",
          "chanceToProfit": "26.73%"
        },
        "full2x": {
          "mean": "20.83",
          "riskOfRuin": "56.63%",
          "stdDev": "140.52",
          "meanExcludingFirstLoss": "137.77",
          "stdDevExcludingFirstLoss": "120.33",
          "chanceToProfit": "39.98%"
        },
        "full4x": {
          "mean": "22.60",
          "riskOfRuin": "77.47%",
          "stdDev": "212.47",
          "meanExcludingFirstLoss": "386.39",
          "stdDevExcludingFirstLoss": "144.35",
          "chanceToProfit": "22.50%"
        },
        "rpsFlat": {
          "mean": "8.34",
          "riskOfRuin": "0.00%",
          "stdDev": "17.36",
          "meanExcludingFirstLoss": "8.34",
          "stdDevExcludingFirstLoss": "17.36",
          "chanceToProfit": "68.55%"
        },
        "rpsHalf2x": {
          "mean": "17.47",
          "riskOfRuin": "59.07%",
          "stdDev": "114.88",
          "meanExcludingFirstLoss": "151.76",
          "stdDevExcludingFirstLoss": "41.46",
          "chanceToProfit": "40.93%"
        },
        "rpsHalf3x": {
          "mean": "19.25",
          "riskOfRuin": "72.99%",
          "stdDev": "159.26",
          "meanExcludingFirstLoss": "275.97",
          "stdDevExcludingFirstLoss": "61.91",
          "chanceToProfit": "26.98%"
        },
        "rpsFull2x": {
          "mean": "16.92",
          "riskOfRuin": "52.58%",
          "stdDev": "113.41",
          "meanExcludingFirstLoss": "129.73",
          "stdDevExcludingFirstLoss": "42.56",
          "chanceToProfit": "47.42%"
        },
        "rpsFull4x": {
          "mean": "20.97",
          "riskOfRuin": "77.47%",
          "stdDev": "203.21",
          "meanExcludingFirstLoss": "379.23",
          "stdDevExcludingFirstLoss": "94.86",
          "chanceToProfit": "22.53%"
        }
      },
      "10": {
        "normal": {
          "mean": "19.63",
          "riskOfRuin": "56.20%",
          "stdDev": "132.69",
          "meanExcludingFirstLoss": "19.63",
          "stdDevExcludingFirstLoss": "132.69",
          "chanceToProfit": "39.42%"
        },
        "half2x": {
          "mean": "20.64",
          "riskOfRuin": "64.96%",
          "stdDev": "153.66",
          "meanExcludingFirstLoss": "159.70",
          "stdDevExcludingFirstLoss": "158.18",
          "chanceToProfit": "33.09%"
        },
        "half3x": {
          "mean": "21.00",
          "riskOfRuin": "73.68%",
          "stdDev": "179.51",
          "meanExcludingFirstLoss": "282.53",
          "stdDevExcludingFirstLoss": "160.95",
          "chanceToProfit": "25.80%"
        },
        "full2x": {
          "mean": "21.10",
          "riskOfRuin": "63.00%",
          "stdDev": "158.48",
          "meanExcludingFirstLoss": "138.25",
          "stdDevExcludingFirstLoss": "160.18",
          "chanceToProfit": "34.40%"
        },
        "full4x": {
          "mean": "22.50",
          "riskOfRuin": "77.68%",
          "stdDev": "218.83",
          "meanExcludingFirstLoss": "386.64",
          "stdDevExcludingFirstLoss": "181.40",
          "chanceToProfit": "22.10%"
        },
        "rpsFlat": {
          "mean": "8.34",
          "riskOfRuin": "0.06%",
          "stdDev": "24.54",
          "meanExcludingFirstLoss": "8.34",
          "stdDevExcludingFirstLoss": "24.54",
          "chanceToProfit": "63.19%"
        },
        "rpsHalf2x": {
          "mean": "17.45",
          "riskOfRuin": "59.08%",
          "stdDev": "115.34",
          "meanExcludingFirstLoss": "151.72",
          "stdDevExcludingFirstLoss": "44.58",
          "chanceToProfit": "40.92%"
        },
        "rpsHalf3x": {
          "mean": "19.30",
          "riskOfRuin": "72.99%",
          "stdDev": "159.51",
          "meanExcludingFirstLoss": "276.03",
          "stdDevExcludingFirstLoss": "63.85",
          "chanceToProfit": "26.99%"
        },
        "rpsFull2x": {
          "mean": "16.87",
          "riskOfRuin": "52.62%",
          "stdDev": "114.02",
          "meanExcludingFirstLoss": "129.77",
          "stdDevExcludingFirstLoss": "45.88",
          "chanceToProfit": "47.38%"
        },
        "rpsFull4x": {
          "mean": "20.83",
          "riskOfRuin": "77.50%",
          "stdDev": "203.29",
          "meanExcludingFirstLoss": "379.30",
          "stdDevExcludingFirstLoss": "96.48",
          "chanceToProfit": "22.50%"
        }
      },
      "15": {
        "normal": {
          "mean": "20.02",
          "riskOfRuin": "62.11%",
          "stdDev": "154.75",
          "meanExcludingFirstLoss": "20.02",
          "stdDevExcludingFirstLoss": "154.75",
          "chanceToProfit": "34.98%"
        },
        "half2x": {
          "mean": "20.78",
          "riskOfRuin": "68.29%",
          "stdDev": "166.78",
          "meanExcludingFirstLoss": "160.03",
          "stdDevExcludingFirstLoss": "187.64",
          "chanceToProfit": "30.12%"
        },
        "half3x": {
          "mean": "21.08",
          "riskOfRuin": "74.66%",
          "stdDev": "187.57",
          "meanExcludingFirstLoss": "282.96",
          "stdDevExcludingFirstLoss": "191.54",
          "chanceToProfit": "24.71%"
        },
        "full2x": {
          "mean": "21.25",
          "riskOfRuin": "67.17%",
          "stdDev": "172.81",
          "meanExcludingFirstLoss": "138.65",
          "stdDevExcludingFirstLoss": "188.60",
          "chanceToProfit": "30.87%"
        },
        "full4x": {
          "mean": "22.36",
          "riskOfRuin": "78.15%",
          "stdDev": "224.55",
          "meanExcludingFirstLoss": "386.04",
          "stdDevExcludingFirstLoss": "211.44",
          "chanceToProfit": "21.48%"
        },
        "rpsFlat": {
          "mean": "8.35",
          "riskOfRuin": "0.48%",
          "stdDev": "29.99",
          "meanExcludingFirstLoss": "8.35",
          "stdDevExcludingFirstLoss": "29.99",
          "chanceToProfit": "61.00%"
        },
        "rpsHalf2x": {
          "mean": "17.48",
          "riskOfRuin": "59.08%",
          "stdDev": "115.86",
          "meanExcludingFirstLoss": "151.80",
          "stdDevExcludingFirstLoss": "47.56",
          "chanceToProfit": "40.92%"
        },
        "rpsHalf3x": {
          "mean": "19.24",
          "riskOfRuin": "73.00%",
          "stdDev": "159.66",
          "meanExcludingFirstLoss": "275.97",
          "stdDevExcludingFirstLoss": "65.71",
          "chanceToProfit": "26.98%"
        },
        "rpsFull2x": {
          "mean": "16.99",
          "riskOfRuin": "52.56%",
          "stdDev": "114.62",
          "meanExcludingFirstLoss": "129.79",
          "stdDevExcludingFirstLoss": "48.88",
          "chanceToProfit": "47.43%"
        },
        "rpsFull4x": {
          "mean": "20.79",
          "riskOfRuin": "77.50%",
          "stdDev": "203.37",
          "meanExcludingFirstLoss": "379.12",
          "stdDevExcludingFirstLoss": "97.58",
          "chanceToProfit": "22.50%"
        }
      },
      "20": {
        "normal": {
          "mean": "20.80",
          "riskOfRuin": "67.60%",
          "stdDev": "168.56",
          "meanExcludingFirstLoss": "20.80",
          "stdDevExcludingFirstLoss": "168.56",
          "chanceToProfit": "30.57%"
        },
        "half2x": {
          "mean": "20.88",
          "riskOfRuin": "70.73%",
          "stdDev": "178.00",
          "meanExcludingFirstLoss": "160.37",
          "stdDevExcludingFirstLoss": "211.18",
          "chanceToProfit": "27.88%"
        },
        "half3x": {
          "mean": "21.03",
          "riskOfRuin": "75.67%",
          "stdDev": "194.74",
          "meanExcludingFirstLoss": "282.90",
          "stdDevExcludingFirstLoss": "216.66",
          "chanceToProfit": "23.66%"
        },
        "full2x": {
          "mean": "21.52",
          "riskOfRuin": "70.57%",
          "stdDev": "184.47",
          "meanExcludingFirstLoss": "139.26",
          "stdDevExcludingFirstLoss": "210.29",
          "chanceToProfit": "28.01%"
        },
        "full4x": {
          "mean": "22.44",
          "riskOfRuin": "78.84%",
          "stdDev": "230.33",
          "meanExcludingFirstLoss": "386.54",
          "stdDevExcludingFirstLoss": "236.89",
          "chanceToProfit": "20.76%"
        },
        "rpsFlat": {
          "mean": "8.39",
          "riskOfRuin": "1.42%",
          "stdDev": "34.58",
          "meanExcludingFirstLoss": "8.39",
          "stdDevExcludingFirstLoss": "34.58",
          "chanceToProfit": "59.81%"
        },
        "rpsHalf2x": {
          "mean": "17.50",
          "riskOfRuin": "59.05%",
          "stdDev": "116.29",
          "meanExcludingFirstLoss": "151.69",
          "stdDevExcludingFirstLoss": "50.24",
          "chanceToProfit": "40.95%"
        },
        "rpsHalf3x": {
          "mean": "19.32",
          "riskOfRuin": "72.97%",
          "stdDev": "159.92",
          "meanExcludingFirstLoss": "276.00",
          "stdDevExcludingFirstLoss": "67.47",
          "chanceToProfit": "27.00%"
        },
        "rpsFull2x": {
          "mean": "16.96",
          "riskOfRuin": "52.56%",
          "stdDev": "115.21",
          "meanExcludingFirstLoss": "129.75",
          "stdDevExcludingFirstLoss": "51.72",
          "chanceToProfit": "47.41%"
        },
        "rpsFull4x": {
          "mean": "20.82",
          "riskOfRuin": "77.50%",
          "stdDev": "203.56",
          "meanExcludingFirstLoss": "379.24",
          "stdDevExcludingFirstLoss": "98.90",
          "chanceToProfit": "22.50%"
        }
      }
    }
  }
]